{
    "features": [
        {
            "geometry": {
                "coordinates": [
                    -76.7066666666667,
                    39.2183333333333
                ],
                "type": "Point"
            },
            "type": "Feature",
            "properties": {
                "state": "MD",
                "nbi_structure_number": "100000030010010",
                "nbi_bridge_id": 436
            }
        },
        {
            "geometry": {
                "coordinates": [
                    [
                        -76.7048312,
                        39.2182574
                    ],
                    [
                        -76.7072075,
                        39.2183424
                    ]
                ],
                "type": "LineString"
            },
            "type": "Feature",
            "properties": {
                "state": "MD",
                "nbi_structure_number": "100000030010010",
                "nbi_bridge_id": 436,
                "maxweight": 32.4,
                "osm_id": 24513923
            }
        },
        {
            "geometry": {
                "coordinates": [
                    [
                        -76.7066231,
                        39.218389
                    ],
                    [
                        -76.7068575,
                        39.2182947
                    ],
                    [
                        -76.7072114,
                        39.2181013
                    ],
                    [
                        -76.7082648,
                        39.217548
                    ],
                    [
                        -76.7091511,
                        39.2170043
                    ]
                ],
                "type": "LineString"
            },
            "type": "Feature",
            "properties": {
                "length": 0.00288560327931361,
                "state": "MD",
                "osm_id": 24513926
            }
        },
        {
            "geometry": {
                "coordinates": [
                    [
                        -76.7054936,
                        39.218166
                    ],
                    [
                        -76.7054025,
                        39.2181961
                    ],
                    [
                        -76.7051476,
                        39.2182907
                    ],
                    [
                        -76.7048808,
                        39.2184018
                    ],
                    [
                        -76.7046058,
                        39.2185483
                    ],
                    [
                        -76.7043497,
                        39.2187094
                    ],
                    [
                        -76.7040801,
                        39.218913
                    ],
                    [
                        -76.7037462,
                        39.2192133
                    ],
                    [
                        -76.7029026,
                        39.2199925
                    ],
                    [
                        -76.7027994,
                        39.2200912
                    ],
                    [
                        -76.7001614,
                        39.2225214
                    ],
                    [
                        -76.7000756,
                        39.2226066
                    ],
                    [
                        -76.6988793,
                        39.2237016
                    ],
                    [
                        -76.698367,
                        39.2241826
                    ],
                    [
                        -76.6979285,
                        39.2246107
                    ]
                ],
                "type": "LineString"
            },
            "type": "Feature",
            "properties": {
                "length": 0.00999410139615855,
                "state": "MD",
                "osm_id": 27081635
            }
        },
        {
            "geometry": {
                "coordinates": [
                    [
                        -76.6979285,
                        39.2246107
                    ],
                    [
                        -76.6984233,
                        39.2242242
                    ],
                    [
                        -76.6989544,
                        39.2237692
                    ],
                    [
                        -76.7001815,
                        39.2226855
                    ],
                    [
                        -76.7002772,
                        39.2225948
                    ],
                    [
                        -76.7010738,
                        39.2218602
                    ],
                    [
                        -76.7015951,
                        39.2213837
                    ],
                    [
                        -76.7029158,
                        39.2201592
                    ],
                    [
                        -76.7030107,
                        39.2200723
                    ],
                    [
                        -76.7038591,
                        39.2192819
                    ],
                    [
                        -76.7041674,
                        39.2189899
                    ],
                    [
                        -76.7044154,
                        39.2187769
                    ],
                    [
                        -76.7046957,
                        39.2185909
                    ],
                    [
                        -76.7049304,
                        39.2184694
                    ],
                    [
                        -76.7051892,
                        39.2183603
                    ],
                    [
                        -76.7055285,
                        39.2182398
                    ]
                ],
                "type": "LineString"
            },
            "type": "Feature",
            "properties": {
                "length": 0.00996843140174044,
                "state": "MD",
                "osm_id": 27081626
            }
        }
    ],
    "type": "FeatureCollection"
}