{
    "features": [
        {
            "geometry": {
                "coordinates": [
                    -76.5583333333333,
                    39.265
                ],
                "type": "Point"
            },
            "type": "Feature",
            "properties": {
                "state": "MD",
                "nbi_structure_number": "300000BCW562010",
                "nbi_bridge_id": 4997
            }
        },
        {
            "geometry": {
                "coordinates": [
                    [
                        -76.5575885,
                        39.2654061
                    ],
                    [
                        -76.557963,
                        39.2654074
                    ],
                    [
                        -76.5580998,
                        39.2654209
                    ],
                    [
                        -76.5582286,
                        39.265449
                    ],
                    [
                        -76.5583613,
                        39.265504
                    ],
                    [
                        -76.5584552,
                        39.2655684
                    ],
                    [
                        -76.5585236,
                        39.2656462
                    ],
                    [
                        -76.5585692,
                        39.2657355
                    ],
                    [
                        -76.5586094,
                        39.2659037
                    ]
                ],
                "type": "LineString"
            },
            "type": "Feature",
            "properties": {
                "state": "MD",
                "nbi_structure_number": "300000BCW562010",
                "nbi_bridge_id": 4997,
                "osm_id": 49796870
            }
        },
        {
            "geometry": {
                "coordinates": [
                    [
                        -76.5643688,
                        39.264161
                    ],
                    [
                        -76.5641488,
                        39.264164
                    ],
                    [
                        -76.5639118,
                        39.264179
                    ],
                    [
                        -76.5633016,
                        39.2641757
                    ],
                    [
                        -76.5631243,
                        39.2641885
                    ],
                    [
                        -76.5630024,
                        39.2641842
                    ],
                    [
                        -76.5628196,
                        39.2642057
                    ],
                    [
                        -76.5626312,
                        39.2642486
                    ],
                    [
                        -76.562271,
                        39.264373
                    ],
                    [
                        -76.5619538,
                        39.264481
                    ],
                    [
                        -76.5613341,
                        39.2646482
                    ],
                    [
                        -76.5610207,
                        39.2647377
                    ],
                    [
                        -76.5608268,
                        39.2647787
                    ],
                    [
                        -76.5605035,
                        39.2648757
                    ],
                    [
                        -76.5600128,
                        39.265009
                    ],
                    [
                        -76.5597027,
                        39.2650892
                    ],
                    [
                        -76.5592464,
                        39.2652073
                    ],
                    [
                        -76.5590468,
                        39.2653832
                    ],
                    [
                        -76.5589423,
                        39.2654293
                    ],
                    [
                        -76.5588894,
                        39.2654384
                    ],
                    [
                        -76.5587148,
                        39.2654866
                    ],
                    [
                        -76.5585485,
                        39.2655324
                    ],
                    [
                        -76.5584781,
                        39.2655811
                    ],
                    [
                        -76.5583918,
                        39.265631
                    ],
                    [
                        -76.5581939,
                        39.265898
                    ],
                    [
                        -76.5580737,
                        39.2661006
                    ],
                    [
                        -76.5579804,
                        39.2662893
                    ],
                    [
                        -76.5579432,
                        39.2663909
                    ]
                ],
                "type": "LineString"
            },
            "type": "Feature",
            "properties": {
                "length": 0.00712399250850178,
                "state": "MD",
                "osm_id": 232677075
            }
        }
    ],
    "type": "FeatureCollection"
}