{
    "features": [
        {
            "geometry": {
                "coordinates": [
                    -77.4416666666667,
                    39.4
                ],
                "type": "Point"
            },
            "type": "Feature",
            "properties": {
                "state": "MD",
                "nbi_structure_number": "100000100141013",
                "nbi_bridge_id": 1229
            }
        },
        {
            "geometry": {
                "coordinates": [
                    [
                        -77.4423738,
                        39.3999461
                    ],
                    [
                        -77.4420568,
                        39.3998028
                    ]
                ],
                "type": "LineString"
            },
            "type": "Feature",
            "properties": {
                "state": "MD",
                "nbi_structure_number": "100000100141013",
                "nbi_bridge_id": 1229,
                "maxweight": 71.1,
                "osm_id": 9405524
            }
        }
    ],
    "type": "FeatureCollection"
}